clifier/__init__.py
clifier/clifier.py
clifier/examples/cli.yaml
clifier/examples/example.py
clifier-0.0.3.dist-info/LICENSE
clifier-0.0.3.dist-info/WHEEL
clifier-0.0.3.dist-info/METADATA
clifier-0.0.3.dist-info/RECORD
